[
  {
    "county_name": "Andover (1)",
    "county_url": "https://locations.tacobell.com/ks/andover",
    "stores": [
      {
        "store_page_url": "https://locations.tacobell.com/ks/andover/336-s-andover-rd.html",
        "store_number": "019957",
        "store_location": "https://www.google.com/maps/dir/?api=1&destination=37.681680836599156,-97.13476274909226"
      }
    ]
  },
  {
    "county_name": "Arkansas City (1)",
    "county_url": "https://locations.tacobell.com/ks/arkansas-city",
    "stores": [
      {
        "store_page_url": "https://locations.tacobell.com/ks/arkansas-city/1745-north-summit-street.html",
        "store_number": "020033",
        "store_location": "https://www.google.com/maps/dir/?api=1&destination=37.0830747604046,-97.04059190800726"
      }
    ]
  },
  {
    "county_name": "Atchison (1)",
    "county_url": "https://locations.tacobell.com/ks/atchison",
    "stores": [
      {
        "store_page_url": "https://locations.tacobell.com/ks/atchison/937-main-st-.html",
        "store_number": "034028",
        "store_location": "https://www.google.com/maps/dir/?api=1&destination=39.561141804379595,-95.12714034991238"
      }
    ]
  },
  {
    "county_name": "Augusta (1)",
    "county_url": "https://locations.tacobell.com/ks/augusta",
    "stores": [
      {
        "store_page_url": "https://locations.tacobell.com/ks/augusta/620-w-7th-ave-.html",
        "store_number": "022521",
        "store_location": "https://www.google.com/maps/dir/?api=1&destination=37.67974242395061,-96.98534115219445"
      }
    ]
  },
  {
    "county_name": "Basehor (1)",
    "county_url": "https://locations.tacobell.com/ks/basehor",
    "stores": [
      {
        "store_page_url": "https://locations.tacobell.com/ks/basehor/15498-state-avenue.html",
        "store_number": "041543",
        "store_location": "https://www.google.com/maps/dir/?api=1&destination=39.116658,-94.938161"
      }
    ]
  },
  {
    "county_name": "Bonner Springs (1)",
    "county_url": "https://locations.tacobell.com/ks/bonner-springs",
    "stores": [
      {
        "store_page_url": "https://locations.tacobell.com/ks/bonner-springs/14-north-130th.html",
        "store_number": "G135023",
        "store_location": "https://www.google.com/maps/dir/?api=1&destination=39.09784700155282,-94.88267143072335"
      }
    ]
  },
  {
    "county_name": "Coffeyville (1)",
    "county_url": "https://locations.tacobell.com/ks/coffeyville",
    "stores": [
      {
        "store_page_url": "https://locations.tacobell.com/ks/coffeyville/1616-west-11th-street.html",
        "store_number": "016743",
        "store_location": "https://www.google.com/maps/dir/?api=1&destination=37.03411153157805,-95.64271427411683"
      }
    ]
  },
  {
    "county_name": "De Soto (1)",
    "county_url": "https://locations.tacobell.com/ks/de-soto",
    "stores": [
      {
        "store_page_url": "https://locations.tacobell.com/ks/de-soto/34070-commerce-drive.html",
        "store_number": "040118",
        "store_location": "https://www.google.com/maps/dir/?api=1&destination=38.96203014735696,-94.9796348542477"
      }
    ]
  },
  {
    "county_name": "Derby (2)",
    "county_url": "https://locations.tacobell.com/ks/derby",
    "stores": [
      {
        "store_page_url": "https://locations.tacobell.com/ks/derby/2127-north-rock-road.html",
        "store_number": "036264",
        "store_location": "https://www.google.com/maps/dir/?api=1&destination=37.56922834953966,-97.24503074910702"
      },
      {
        "store_page_url": "https://locations.tacobell.com/ks/derby/957-n-buckner.html",
        "store_number": "003968",
        "store_location": "https://www.google.com/maps/dir/?api=1&destination=37.553189565728616,-97.2716859522256"
      }
    ]
  },
  {
    "county_name": "Dodge City (1)",
    "county_url": "https://locations.tacobell.com/ks/dodge-city",
    "stores": [
      {
        "store_page_url": "https://locations.tacobell.com/ks/dodge-city/708-west-wyatt-earp-road.html",
        "store_number": "015610",
        "store_location": "https://www.google.com/maps/dir/?api=1&destination=37.753619726109186,-100.02382557774057"
      }
    ]
  },
  {
    "county_name": "El Dorado (1)",
    "county_url": "https://locations.tacobell.com/ks/el-dorado",
    "stores": [
      {
        "store_page_url": "https://locations.tacobell.com/ks/el-dorado/721-north-main-street.html",
        "store_number": "019348",
        "store_location": "https://www.google.com/maps/dir/?api=1&destination=37.82568405967351,-96.84989231015076"
      }
    ]
  },
  {
    "county_name": "Emporia (2)",
    "county_url": "https://locations.tacobell.com/ks/emporia",
    "stores": [
      {
        "store_page_url": "https://locations.tacobell.com/ks/emporia/2807-eaglecrest-drive.html",
        "store_number": "024469",
        "store_location": "https://www.google.com/maps/dir/?api=1&destination=38.42286831291317,-96.21750672148545"
      },
      {
        "store_page_url": "https://locations.tacobell.com/ks/emporia/1407-w-sixth-avenue.html",
        "store_number": "024465",
        "store_location": "https://www.google.com/maps/dir/?api=1&destination=38.404629048244445,-96.19775354862213"
      }
    ]
  },
  {
    "county_name": "Fort Scott (1)",
    "county_url": "https://locations.tacobell.com/ks/fort-scott",
    "stores": [
      {
        "store_page_url": "https://locations.tacobell.com/ks/fort-scott/2305-south-main.html",
        "store_number": "020463",
        "store_location": "https://www.google.com/maps/dir/?api=1&destination=37.81266160776843,-94.70495671033859"
      }
    ]
  },
  {
    "county_name": "Garden City (1)",
    "county_url": "https://locations.tacobell.com/ks/garden-city",
    "stores": [
      {
        "store_page_url": "https://locations.tacobell.com/ks/garden-city/2408-east-kansas-ave.html",
        "store_number": "029458",
        "store_location": "https://www.google.com/maps/dir/?api=1&destination=37.97917739499902,-100.84140488508638"
      }
    ]
  },
  {
    "county_name": "Gardner (2)",
    "county_url": "https://locations.tacobell.com/ks/gardner",
    "stores": [
      {
        "store_page_url": "https://locations.tacobell.com/ks/gardner/651-east-main-street.html",
        "store_number": "K071016",
        "store_location": "https://www.google.com/maps/dir/?api=1&destination=38.810672508291276,-94.91367012262344"
      },
      {
        "store_page_url": "https://locations.tacobell.com/ks/gardner/18731-s-gardner-rd.html",
        "store_number": "041986",
        "store_location": "https://www.google.com/maps/dir/?api=1&destination=38.78823840506448,-94.92682552690782"
      }
    ]
  },
  {
    "county_name": "Goddard (1)",
    "county_url": "https://locations.tacobell.com/ks/goddard",
    "stores": [
      {
        "store_page_url": "https://locations.tacobell.com/ks/goddard/20075-west-kellogg-drive.html",
        "store_number": "021366",
        "store_location": "https://www.google.com/maps/dir/?api=1&destination=37.66358691725048,-97.57273748522493"
      }
    ]
  },
  {
    "county_name": "Great Bend (1)",
    "county_url": "https://locations.tacobell.com/ks/great-bend",
    "stores": [
      {
        "store_page_url": "https://locations.tacobell.com/ks/great-bend/3607-west-10th-street.html",
        "store_number": "016993",
        "store_location": "https://www.google.com/maps/dir/?api=1&destination=38.361389212445836,-98.78795383998272"
      }
    ]
  },
  {
    "county_name": "Hays (1)",
    "county_url": "https://locations.tacobell.com/ks/hays",
    "stores": [
      {
        "store_page_url": "https://locations.tacobell.com/ks/hays/1730-vine-street.html",
        "store_number": "019507",
        "store_location": "https://www.google.com/maps/dir/?api=1&destination=38.87406357456446,-99.31730054324362"
      }
    ]
  },
  {
    "county_name": "Holton (1)",
    "county_url": "https://locations.tacobell.com/ks/holton",
    "stores": [
      {
        "store_page_url": "https://locations.tacobell.com/ks/holton/105-us-highway-75.html",
        "store_number": "020719",
        "store_location": "https://www.google.com/maps/dir/?api=1&destination=39.457287878498335,-95.74859668045401"
      }
    ]
  },
  {
    "county_name": "Hutchinson (2)",
    "county_url": "https://locations.tacobell.com/ks/hutchinson",
    "stores": [
      {
        "store_page_url": "https://locations.tacobell.com/ks/hutchinson/412-e-4th-ave.html",
        "store_number": "003778",
        "store_location": "https://www.google.com/maps/dir/?api=1&destination=38.057605952517804,-97.92320141110706"
      },
      {
        "store_page_url": "https://locations.tacobell.com/ks/hutchinson/1203-e-30th-st.html",
        "store_number": "005282",
        "store_location": "https://www.google.com/maps/dir/?api=1&destination=38.086117163283426,-97.90707940242967"
      }
    ]
  },
  {
    "county_name": "Independence (1)",
    "county_url": "https://locations.tacobell.com/ks/independence",
    "stores": [
      {
        "store_page_url": "https://locations.tacobell.com/ks/independence/305-n-8th-st.html",
        "store_number": "021199",
        "store_location": "https://www.google.com/maps/dir/?api=1&destination=37.22603378518892,-95.70843373240677"
      }
    ]
  },
  {
    "county_name": "Iola (1)",
    "county_url": "https://locations.tacobell.com/ks/iola",
    "stores": [
      {
        "store_page_url": "https://locations.tacobell.com/ks/iola/1602-north-state-street.html",
        "store_number": "017457",
        "store_location": "https://www.google.com/maps/dir/?api=1&destination=37.93696648776899,-95.40970806779114"
      }
    ]
  },
  {
    "county_name": "Junction City (2)",
    "county_url": "https://locations.tacobell.com/ks/junction-city",
    "stores": [
      {
        "store_page_url": "https://locations.tacobell.com/ks/junction-city/631-e-chestnut-st.html",
        "store_number": "023229",
        "store_location": "https://www.google.com/maps/dir/?api=1&destination=39.021126277624376,-96.81963095072206"
      },
      {
        "store_page_url": "https://locations.tacobell.com/ks/junction-city/407-w--18th-street.html",
        "store_number": "024109",
        "store_location": "https://www.google.com/maps/dir/?api=1&destination=39.041167528027316,-96.83602541685104"
      }
    ]
  },
  {
    "county_name": "Kansas City (6)",
    "county_url": "https://locations.tacobell.com/ks/kansas-city",
    "stores": [
      {
        "store_page_url": "https://locations.tacobell.com/ks/kansas-city/7337-state-ave.html",
        "store_number": "034381",
        "store_location": "https://www.google.com/maps/dir/?api=1&destination=39.11624557910572,-94.7494626045227"
      },
      {
        "store_page_url": "https://locations.tacobell.com/ks/kansas-city/635-s-7th-st.html",
        "store_number": "G135017",
        "store_location": "https://www.google.com/maps/dir/?api=1&destination=39.086441298307314,-94.62531843784745"
      },
      {
        "store_page_url": "https://locations.tacobell.com/ks/kansas-city/4401-shawnee-drive.html",
        "store_number": "G135013",
        "store_location": "https://www.google.com/maps/dir/?api=1&destination=39.05294653041414,-94.68099430394038"
      },
      {
        "store_page_url": "https://locations.tacobell.com/ks/kansas-city/3948-rainbow-blvd.html",
        "store_number": "034412",
        "store_location": "https://www.google.com/maps/dir/?api=1&destination=39.055370215700385,-94.61215288193671"
      },
      {
        "store_page_url": "https://locations.tacobell.com/ks/kansas-city/3651-state-avenue.html",
        "store_number": "034380",
        "store_location": "https://www.google.com/maps/dir/?api=1&destination=39.11631009128362,-94.67128559947014"
      },
      {
        "store_page_url": "https://locations.tacobell.com/ks/kansas-city/10540-parallel-parkway.html",
        "store_number": "034394",
        "store_location": "https://www.google.com/maps/dir/?api=1&destination=39.12901809821786,-94.82332013550149"
      }
    ]
  },
  {
    "county_name": "Larned (1)",
    "county_url": "https://locations.tacobell.com/ks/larned",
    "stores": [
      {
        "store_page_url": "https://locations.tacobell.com/ks/larned/102-e-14th-st.html",
        "store_number": "031068",
        "store_location": "https://www.google.com/maps/dir/?api=1&destination=38.187862,-99.098035"
      }
    ]
  },
  {
    "county_name": "Lawrence (3)",
    "county_url": "https://locations.tacobell.com/ks/lawrence",
    "stores": [
      {
        "store_page_url": "https://locations.tacobell.com/ks/lawrence/4721-bauer-farm-drive.html",
        "store_number": "025719",
        "store_location": "https://www.google.com/maps/dir/?api=1&destination=38.9719953896984,-95.30387046423174"
      },
      {
        "store_page_url": "https://locations.tacobell.com/ks/lawrence/1408-w-23rd-st.html",
        "store_number": "024464",
        "store_location": "https://www.google.com/maps/dir/?api=1&destination=38.94308447290538,-95.25115766215166"
      },
      {
        "store_page_url": "https://locations.tacobell.com/ks/lawrence/1220-w-6th-st.html",
        "store_number": "024466",
        "store_location": "https://www.google.com/maps/dir/?api=1&destination=38.9735010861084,-95.24973294344153"
      }
    ]
  },
  {
    "county_name": "Leavenworth (2)",
    "county_url": "https://locations.tacobell.com/ks/leavenworth",
    "stores": [
      {
        "store_page_url": "https://locations.tacobell.com/ks/leavenworth/2925-s-4th-st-.html",
        "store_number": "035230",
        "store_location": "https://www.google.com/maps/dir/?api=1&destination=39.287830023662785,-94.90550809116128"
      },
      {
        "store_page_url": "https://locations.tacobell.com/ks/leavenworth/601-metropolitan-ave.html",
        "store_number": "037673",
        "store_location": "https://www.google.com/maps/dir/?api=1&destination=39.327966935941134,-94.91933786762141"
      }
    ]
  },
  {
    "county_name": "Lenexa (3)",
    "county_url": "https://locations.tacobell.com/ks/lenexa",
    "stores": [
      {
        "store_page_url": "https://locations.tacobell.com/ks/lenexa/9600-quivira-rd-.html",
        "store_number": "034397",
        "store_location": "https://www.google.com/maps/dir/?api=1&destination=38.95415481202508,-94.72412779927254"
      },
      {
        "store_page_url": "https://locations.tacobell.com/ks/lenexa/16130-w-87th-street.html",
        "store_number": "034392",
        "store_location": "https://www.google.com/maps/dir/?api=1&destination=38.97159635996853,-94.77385729551315"
      },
      {
        "store_page_url": "https://locations.tacobell.com/ks/lenexa/12291-w-87th-st.html",
        "store_number": "034396",
        "store_location": "https://www.google.com/maps/dir/?api=1&destination=38.97063379095861,-94.72790113945045"
      }
    ]
  },
  {
    "county_name": "Liberal (1)",
    "county_url": "https://locations.tacobell.com/ks/liberal",
    "stores": [
      {
        "store_page_url": "https://locations.tacobell.com/ks/liberal/1720-north-kansas-ave.html",
        "store_number": "020464",
        "store_location": "https://www.google.com/maps/dir/?api=1&destination=37.05679801802616,-100.92289675771708"
      }
    ]
  },
  {
    "county_name": "Maize (1)",
    "county_url": "https://locations.tacobell.com/ks/maize",
    "stores": [
      {
        "store_page_url": "https://locations.tacobell.com/ks/maize/4000-north-maize-road.html",
        "store_number": "023152",
        "store_location": "https://www.google.com/maps/dir/?api=1&destination=37.75570855455105,-97.46239364147186"
      }
    ]
  },
  {
    "county_name": "Manhattan (2)",
    "county_url": "https://locations.tacobell.com/ks/manhattan",
    "stores": [
      {
        "store_page_url": "https://locations.tacobell.com/ks/manhattan/1009-limey-pointe.html",
        "store_number": "024102",
        "store_location": "https://www.google.com/maps/dir/?api=1&destination=39.18991346751252,-96.55859072508065"
      },
      {
        "store_page_url": "https://locations.tacobell.com/ks/manhattan/1155-westport-road.html",
        "store_number": "002518",
        "store_location": "https://www.google.com/maps/dir/?api=1&destination=39.19256372557171,-96.60670072655194"
      }
    ]
  },
  {
    "county_name": "McPherson (1)",
    "county_url": "https://locations.tacobell.com/ks/mcpherson",
    "stores": [
      {
        "store_page_url": "https://locations.tacobell.com/ks/mcpherson/2115-east-kansas-avenue.html",
        "store_number": "019919",
        "store_location": "https://www.google.com/maps/dir/?api=1&destination=38.3714997294763,-97.62719986638527"
      }
    ]
  },
  {
    "county_name": "Merriam (1)",
    "county_url": "https://locations.tacobell.com/ks/merriam",
    "stores": [
      {
        "store_page_url": "https://locations.tacobell.com/ks/merriam/5930-ikea-way.html",
        "store_number": "034414",
        "store_location": "https://www.google.com/maps/dir/?api=1&destination=39.021063345472584,-94.69070076942444"
      }
    ]
  },
  {
    "county_name": "Mission (1)",
    "county_url": "https://locations.tacobell.com/ks/mission",
    "stores": [
      {
        "store_page_url": "https://locations.tacobell.com/ks/mission/6350-johnson-dr.html",
        "store_number": "037462",
        "store_location": "https://www.google.com/maps/dir/?api=1&destination=39.02263611116933,-94.65944396415333"
      }
    ]
  },
  {
    "county_name": "Mulvane (1)",
    "county_url": "https://locations.tacobell.com/ks/mulvane",
    "stores": [
      {
        "store_page_url": "https://locations.tacobell.com/ks/mulvane/1255-n--rock-road.html",
        "store_number": "026915",
        "store_location": "https://www.google.com/maps/dir/?api=1&destination=37.488506205071076,-97.24517950418885"
      }
    ]
  },
  {
    "county_name": "Newton (1)",
    "county_url": "https://locations.tacobell.com/ks/newton",
    "stores": [
      {
        "store_page_url": "https://locations.tacobell.com/ks/newton/1403-north-main.html",
        "store_number": "015958",
        "store_location": "https://www.google.com/maps/dir/?api=1&destination=38.05843881942488,-97.34563484793398"
      }
    ]
  },
  {
    "county_name": "Olathe (6)",
    "county_url": "https://locations.tacobell.com/ks/olathe",
    "stores": [
      {
        "store_page_url": "https://locations.tacobell.com/ks/olathe/14189-w-135th-st.html",
        "store_number": "042175",
        "store_location": "https://www.google.com/maps/dir/?api=1&destination=38.88305,-94.75035"
      },
      {
        "store_page_url": "https://locations.tacobell.com/ks/olathe/15109-w--151st-st-.html",
        "store_number": "034416",
        "store_location": "https://www.google.com/maps/dir/?api=1&destination=38.85447723457318,-94.76182009680939"
      },
      {
        "store_page_url": "https://locations.tacobell.com/ks/olathe/14880-south-harrison.html",
        "store_number": "034386",
        "store_location": "https://www.google.com/maps/dir/?api=1&destination=38.858548,-94.816696"
      },
      {
        "store_page_url": "https://locations.tacobell.com/ks/olathe/12075-s--blackbob-rd-.html",
        "store_number": "034401",
        "store_location": "https://www.google.com/maps/dir/?api=1&destination=38.909992641575855,-94.76036846637726"
      },
      {
        "store_page_url": "https://locations.tacobell.com/ks/olathe/1117-e--santa-fe-st-.html",
        "store_number": "034402",
        "store_location": "https://www.google.com/maps/dir/?api=1&destination=38.883297571806565,-94.79842230677605"
      },
      {
        "store_page_url": "https://locations.tacobell.com/ks/olathe/10546-s-ridgeview.html",
        "store_number": "036456",
        "store_location": "https://www.google.com/maps/dir/?api=1&destination=38.93736145324491,-94.79853536458671"
      }
    ]
  },
  {
    "county_name": "Ottawa (1)",
    "county_url": "https://locations.tacobell.com/ks/ottawa",
    "stores": [
      {
        "store_page_url": "https://locations.tacobell.com/ks/ottawa/2304-princeton-st.html",
        "store_number": "004773",
        "store_location": "https://www.google.com/maps/dir/?api=1&destination=38.57897214543114,-95.2681884169578"
      }
    ]
  },
  {
    "county_name": "Overland Park (7)",
    "county_url": "https://locations.tacobell.com/ks/overland-park",
    "stores": [
      {
        "store_page_url": "https://locations.tacobell.com/ks/overland-park/9690-metcalf-ave-.html",
        "store_number": "034403",
        "store_location": "https://www.google.com/maps/dir/?api=1&destination=38.95354939103666,-94.66823749246947"
      },
      {
        "store_page_url": "https://locations.tacobell.com/ks/overland-park/8559-west-135th-st-.html",
        "store_number": "034404",
        "store_location": "https://www.google.com/maps/dir/?api=1&destination=38.883233264398655,-94.68413659933503"
      },
      {
        "store_page_url": "https://locations.tacobell.com/ks/overland-park/8000-w--151st-st-.html",
        "store_number": "035231",
        "store_location": "https://www.google.com/maps/dir/?api=1&destination=38.8549768003914,-94.68013815117047"
      },
      {
        "store_page_url": "https://locations.tacobell.com/ks/overland-park/12208-college-blvd.html",
        "store_number": "034398",
        "store_location": "https://www.google.com/maps/dir/?api=1&destination=38.927947790963614,-94.7288228726241"
      },
      {
        "store_page_url": "https://locations.tacobell.com/ks/overland-park/10107-w--75th-street.html",
        "store_number": "034390",
        "store_location": "https://www.google.com/maps/dir/?api=1&destination=38.99264021027865,-94.70314487814898"
      },
      {
        "store_page_url": "https://locations.tacobell.com/ks/overland-park/7100-w--119th-st.html",
        "store_number": "036695",
        "store_location": "https://www.google.com/maps/dir/?api=1&destination=38.91437293002071,-94.66991543529592"
      },
      {
        "store_page_url": "https://locations.tacobell.com/ks/overland-park/15881-metcalf-avenue.html",
        "store_number": "040327",
        "store_location": "https://www.google.com/maps/dir/?api=1&destination=38.8421264,-94.6664242"
      }
    ]
  },
  {
    "county_name": "Paola (1)",
    "county_url": "https://locations.tacobell.com/ks/paola",
    "stores": [
      {
        "store_page_url": "https://locations.tacobell.com/ks/paola/201-south-angela-street.html",
        "store_number": "G135255",
        "store_location": "https://www.google.com/maps/dir/?api=1&destination=38.57186875916217,-94.85934420774439"
      }
    ]
  },
  {
    "county_name": "Park City (1)",
    "county_url": "https://locations.tacobell.com/ks/park-city",
    "stores": [
      {
        "store_page_url": "https://locations.tacobell.com/ks/park-city/950-connolly-ct.html",
        "store_number": "020154",
        "store_location": "https://www.google.com/maps/dir/?api=1&destination=37.79746704407689,-97.32718710602967"
      }
    ]
  },
  {
    "county_name": "Parsons (1)",
    "county_url": "https://locations.tacobell.com/ks/parsons",
    "stores": [
      {
        "store_page_url": "https://locations.tacobell.com/ks/parsons/301-n--16th-street.html",
        "store_number": "033582",
        "store_location": "https://www.google.com/maps/dir/?api=1&destination=37.34224726372693,-95.25867769444275"
      }
    ]
  },
  {
    "county_name": "Pittsburg (1)",
    "county_url": "https://locations.tacobell.com/ks/pittsburg",
    "stores": [
      {
        "store_page_url": "https://locations.tacobell.com/ks/pittsburg/1115-s-broadway-st.html",
        "store_number": "004177",
        "store_location": "https://www.google.com/maps/dir/?api=1&destination=37.3977737492647,-94.7045007138513"
      }
    ]
  },
  {
    "county_name": "Pratt (1)",
    "county_url": "https://locations.tacobell.com/ks/pratt",
    "stores": [
      {
        "store_page_url": "https://locations.tacobell.com/ks/pratt/2007-e-1st-st.html",
        "store_number": "024463",
        "store_location": "https://www.google.com/maps/dir/?api=1&destination=37.64499595149334,-98.71218395284052"
      }
    ]
  },
  {
    "county_name": "Roeland Park (1)",
    "county_url": "https://locations.tacobell.com/ks/roeland-park",
    "stores": [
      {
        "store_page_url": "https://locations.tacobell.com/ks/roeland-park/5004-roe-blvd-.html",
        "store_number": "034413",
        "store_location": "https://www.google.com/maps/dir/?api=1&destination=39.03716305334013,-94.64013998236736"
      }
    ]
  },
  {
    "county_name": "Salina (3)",
    "county_url": "https://locations.tacobell.com/ks/salina",
    "stores": [
      {
        "store_page_url": "https://locations.tacobell.com/ks/salina/2305-s-9th-st.html",
        "store_number": "029416",
        "store_location": "https://www.google.com/maps/dir/?api=1&destination=38.8006483258379,-97.61193114030331"
      },
      {
        "store_page_url": "https://locations.tacobell.com/ks/salina/1700-w-crawford.html",
        "store_number": "023231",
        "store_location": "https://www.google.com/maps/dir/?api=1&destination=38.82750951411898,-97.63340817199335"
      },
      {
        "store_page_url": "https://locations.tacobell.com/ks/salina/1040-e-iron-ave.html",
        "store_number": "023230",
        "store_location": "https://www.google.com/maps/dir/?api=1&destination=38.84009620034588,-97.59439051151276"
      }
    ]
  },
  {
    "county_name": "Shawnee Mission (1)",
    "county_url": "https://locations.tacobell.com/ks/shawnee-mission",
    "stores": [
      {
        "store_page_url": "https://locations.tacobell.com/ks/shawnee-mission/12014-shawnee-mission-pkwy-.html",
        "store_number": "034400",
        "store_location": "https://www.google.com/maps/dir/?api=1&destination=39.015331458797995,-94.72575337509625"
      }
    ]
  },
  {
    "county_name": "Tecumseh (1)",
    "county_url": "https://locations.tacobell.com/ks/tecumseh",
    "stores": [
      {
        "store_page_url": "https://locations.tacobell.com/ks/tecumseh/e-topeka-service-area-2-8000.html",
        "store_number": "30461",
        "store_location": "https://www.google.com/maps/dir/?api=1&destination=39.019547,-95.508819"
      }
    ]
  },
  {
    "county_name": "Topeka (3)",
    "county_url": "https://locations.tacobell.com/ks/topeka",
    "stores": [
      {
        "store_page_url": "https://locations.tacobell.com/ks/topeka/2013-nw-topeka-blvd.html",
        "store_number": "002329",
        "store_location": "https://www.google.com/maps/dir/?api=1&destination=39.08599868095965,-95.6655022949144"
      },
      {
        "store_page_url": "https://locations.tacobell.com/ks/topeka/1560-s-w--wanamaker-rd.html",
        "store_number": "004120",
        "store_location": "https://www.google.com/maps/dir/?api=1&destination=39.03836518191212,-95.76130165064725"
      },
      {
        "store_page_url": "https://locations.tacobell.com/ks/topeka/101-se-29th-street.html",
        "store_number": "002274",
        "store_location": "https://www.google.com/maps/dir/?api=1&destination=39.0147877694527,-95.6812978238031"
      }
    ]
  },
  {
    "county_name": "Wellington (1)",
    "county_url": "https://locations.tacobell.com/ks/wellington",
    "stores": [
      {
        "store_page_url": "https://locations.tacobell.com/ks/wellington/1180-e--16th-street.html",
        "store_number": "034822",
        "store_location": "https://www.google.com/maps/dir/?api=1&destination=37.27489554712962,-97.38358876530708"
      }
    ]
  },
  {
    "county_name": "Wichita (15)",
    "county_url": "https://locations.tacobell.com/ks/wichita",
    "stores": [
      {
        "store_page_url": "https://locations.tacobell.com/ks/wichita/3455-south-meridian-.html",
        "store_number": "022686",
        "store_location": "https://www.google.com/maps/dir/?api=1&destination=37.63112940178384,-97.37145490947114"
      },
      {
        "store_page_url": "https://locations.tacobell.com/ks/wichita/328-s-west-st.html",
        "store_number": "021178",
        "store_location": "https://www.google.com/maps/dir/?api=1&destination=37.6792948258498,-97.38889266552178"
      },
      {
        "store_page_url": "https://locations.tacobell.com/ks/wichita/2230-north-rock-rd.html",
        "store_number": "003790",
        "store_location": "https://www.google.com/maps/dir/?api=1&destination=37.72405205368808,-97.24410453377793"
      },
      {
        "store_page_url": "https://locations.tacobell.com/ks/wichita/2707-west-53rd-street.html",
        "store_number": "041266",
        "store_location": "https://www.google.com/maps/dir/?api=1&destination=37.781804,-97.375357"
      },
      {
        "store_page_url": "https://locations.tacobell.com/ks/wichita/1919-w-21st-st-n.html",
        "store_number": "003777",
        "store_location": "https://www.google.com/maps/dir/?api=1&destination=37.72235326752558,-97.36191366614548"
      },
      {
        "store_page_url": "https://locations.tacobell.com/ks/wichita/1695-s-webb-rd.html",
        "store_number": "032053",
        "store_location": "https://www.google.com/maps/dir/?api=1&destination=37.662683890037535,-97.22671548346716"
      },
      {
        "store_page_url": "https://locations.tacobell.com/ks/wichita/5808-e-central.html",
        "store_number": "004523",
        "store_location": "https://www.google.com/maps/dir/?api=1&destination=37.694239846760134,-97.26898808847181"
      },
      {
        "store_page_url": "https://locations.tacobell.com/ks/wichita/422-east-47th-south.html",
        "store_number": "003829",
        "store_location": "https://www.google.com/maps/dir/?api=1&destination=37.608343127816866,-97.33147562296836"
      },
      {
        "store_page_url": "https://locations.tacobell.com/ks/wichita/6515-e-37th-st-n.html",
        "store_number": "021337",
        "store_location": "https://www.google.com/maps/dir/?api=1&destination=37.751678133854746,-97.26006246638468"
      },
      {
        "store_page_url": "https://locations.tacobell.com/ks/wichita/2432-s-seneca.html",
        "store_number": "004381",
        "store_location": "https://www.google.com/maps/dir/?api=1&destination=37.65033488550329,-97.35217924700235"
      },
      {
        "store_page_url": "https://locations.tacobell.com/ks/wichita/11877-e-kellogg.html",
        "store_number": "021307",
        "store_location": "https://www.google.com/maps/dir/?api=1&destination=37.67858346562989,-97.19969809055328"
      },
      {
        "store_page_url": "https://locations.tacobell.com/ks/wichita/8979-w-central.html",
        "store_number": "023047",
        "store_location": "https://www.google.com/maps/dir/?api=1&destination=37.693617950197684,-97.44749126723036"
      },
      {
        "store_page_url": "https://locations.tacobell.com/ks/wichita/7301-west-21st-street.html",
        "store_number": "016744",
        "store_location": "https://www.google.com/maps/dir/?api=1&destination=37.722700961641145,-97.42752491380088"
      },
      {
        "store_page_url": "https://locations.tacobell.com/ks/wichita/3216-e--harry-st-.html",
        "store_number": "042112",
        "store_location": "https://www.google.com/maps/dir/?api=1&destination=37.6648,-97.2982"
      },
      {
        "store_page_url": "https://locations.tacobell.com/ks/wichita/11155-e-29th-st-n.html",
        "store_number": "042417",
        "store_location": "https://www.google.com/maps/dir/?api=1&destination=37.73724,-97.208302"
      }
    ]
  },
  {
    "county_name": "Winfield (1)",
    "county_url": "https://locations.tacobell.com/ks/winfield",
    "stores": []
  }
]