[
  {
    "county_name": "Aberdeen (1)",
    "county_url": "https://locations.tacobell.com/wa/aberdeen",
    "stores": [
      {
        "store_page_url": "https://locations.tacobell.com/wa/aberdeen/1120-e-wishkah-st.html",
        "store_number": "031333",
        "store_location": "https://www.google.com/maps/dir/?api=1&destination=46.977586434868314,-123.80351731184419"
      }
    ]
  },
  {
    "county_name": "Auburn (2)",
    "county_url": "https://locations.tacobell.com/wa/auburn",
    "stores": [
      {
        "store_page_url": "https://locations.tacobell.com/wa/auburn/710-auburn-way-s.html",
        "store_number": "035310",
        "store_location": "https://www.google.com/maps/dir/?api=1&destination=47.30063775943571,-122.22394108772278"
      },
      {
        "store_page_url": "https://locations.tacobell.com/wa/auburn/501-15th-st--n-e-.html",
        "store_number": "035307",
        "store_location": "https://www.google.com/maps/dir/?api=1&destination=47.321116011366755,-122.22369968891144"
      }
    ]
  },
  {
    "county_name": "Battle Ground (1)",
    "county_url": "https://locations.tacobell.com/wa/battle-ground",
    "stores": [
      {
        "store_page_url": "https://locations.tacobell.com/wa/battle-ground/1702-west-main-street.html",
        "store_number": "021046",
        "store_location": "https://www.google.com/maps/dir/?api=1&destination=45.7808883263527,-122.55509443582469"
      }
    ]
  },
  {
    "county_name": "Belfair (1)",
    "county_url": "https://locations.tacobell.com/wa/belfair",
    "stores": [
      {
        "store_page_url": "https://locations.tacobell.com/wa/belfair/23881-ne-hwy-3.html",
        "store_number": "037299",
        "store_location": "https://www.google.com/maps/dir/?api=1&destination=47.45281310681201,-122.82450069487709"
      }
    ]
  },
  {
    "county_name": "Bellevue (1)",
    "county_url": "https://locations.tacobell.com/wa/bellevue",
    "stores": [
      {
        "store_page_url": "https://locations.tacobell.com/wa/bellevue/3705-128th-ave-s-e.html",
        "store_number": "022598",
        "store_location": "https://www.google.com/maps/dir/?api=1&destination=47.57727376715472,-122.16985995407414"
      }
    ]
  },
  {
    "county_name": "Bellingham (2)",
    "county_url": "https://locations.tacobell.com/wa/bellingham",
    "stores": [
      {
        "store_page_url": "https://locations.tacobell.com/wa/bellingham/1297-e--sunset-dr-.html",
        "store_number": "041262",
        "store_location": "https://www.google.com/maps/dir/?api=1&destination=48.77323072844714,-122.45833316448625"
      },
      {
        "store_page_url": "https://locations.tacobell.com/wa/bellingham/100-east-stuart-rd-.html",
        "store_number": "041263",
        "store_location": "https://www.google.com/maps/dir/?api=1&destination=48.8004433915814,-122.4854203035527"
      }
    ]
  },
  {
    "county_name": "Blaine (1)",
    "county_url": "https://locations.tacobell.com/wa/blaine",
    "stores": [
      {
        "store_page_url": "https://locations.tacobell.com/wa/blaine/805-grant-ave-.html",
        "store_number": "040354",
        "store_location": "https://www.google.com/maps/dir/?api=1&destination=48.993170332711436,-122.7338138411024"
      }
    ]
  },
  {
    "county_name": "Bonney Lake (1)",
    "county_url": "https://locations.tacobell.com/wa/bonney-lake",
    "stores": [
      {
        "store_page_url": "https://locations.tacobell.com/wa/bonney-lake/21131-state-route-410-e.html",
        "store_number": "035309",
        "store_location": "https://www.google.com/maps/dir/?api=1&destination=47.16724952491862,-122.14686512947083"
      }
    ]
  },
  {
    "county_name": "Bothell (2)",
    "county_url": "https://locations.tacobell.com/wa/bothell",
    "stores": [
      {
        "store_page_url": "https://locations.tacobell.com/wa/bothell/23201-bothell-everett-hwy.html",
        "store_number": "022606",
        "store_location": "https://www.google.com/maps/dir/?api=1&destination=47.78756701067176,-122.21865788951004"
      },
      {
        "store_page_url": "https://locations.tacobell.com/wa/bothell/18001-bothell-everett-hwy.html",
        "store_number": "034919",
        "store_location": "https://www.google.com/maps/dir/?api=1&destination=47.834354019312364,-122.21010247217036"
      }
    ]
  },
  {
    "county_name": "Bremerton (2)",
    "county_url": "https://locations.tacobell.com/wa/bremerton",
    "stores": [
      {
        "store_page_url": "https://locations.tacobell.com/wa/bremerton/7150-state-route-303.html",
        "store_number": "042280",
        "store_location": "https://www.google.com/maps/dir/?api=1&destination=47.62750624321519,-122.6284585666023"
      },
      {
        "store_page_url": "https://locations.tacobell.com/wa/bremerton/3320-kitsap-way.html",
        "store_number": "042282",
        "store_location": "https://www.google.com/maps/dir/?api=1&destination=47.57193679493281,-122.66019165515894"
      }
    ]
  },
  {
    "county_name": "Burien (1)",
    "county_url": "https://locations.tacobell.com/wa/burien",
    "stores": [
      {
        "store_page_url": "https://locations.tacobell.com/wa/burien/15059-1st-ave-s.html",
        "store_number": "031319",
        "store_location": "https://www.google.com/maps/dir/?api=1&destination=47.46716820363549,-122.33425765181892"
      }
    ]
  },
  {
    "county_name": "Burlington (1)",
    "county_url": "https://locations.tacobell.com/wa/burlington",
    "stores": [
      {
        "store_page_url": "https://locations.tacobell.com/wa/burlington/1308-burlington-blvd-.html",
        "store_number": "031345",
        "store_location": "https://www.google.com/maps/dir/?api=1&destination=48.460744238766864,-122.33527556061745"
      }
    ]
  },
  {
    "county_name": "Camas (1)",
    "county_url": "https://locations.tacobell.com/wa/camas",
    "stores": [
      {
        "store_page_url": "https://locations.tacobell.com/wa/camas/3405-ne-3rd-ave.html",
        "store_number": "017226",
        "store_location": "https://www.google.com/maps/dir/?api=1&destination=45.58506299586139,-122.3691728203765"
      }
    ]
  },
  {
    "county_name": "Centralia (1)",
    "county_url": "https://locations.tacobell.com/wa/centralia",
    "stores": [
      {
        "store_page_url": "https://locations.tacobell.com/wa/centralia/1120-belmont-ave.html",
        "store_number": "031347",
        "store_location": "https://www.google.com/maps/dir/?api=1&destination=46.72933065021025,-122.97925651073456"
      }
    ]
  },
  {
    "county_name": "Chehalis (1)",
    "county_url": "https://locations.tacobell.com/wa/chehalis",
    "stores": [
      {
        "store_page_url": "https://locations.tacobell.com/wa/chehalis/1755-nw-louisiana-ave.html",
        "store_number": "032471",
        "store_location": "https://www.google.com/maps/dir/?api=1&destination=46.68071272778021,-122.97519422135224"
      }
    ]
  },
  {
    "county_name": "Cheney (1)",
    "county_url": "https://locations.tacobell.com/wa/cheney",
    "stores": [
      {
        "store_page_url": "https://locations.tacobell.com/wa/cheney/2626-first-street.html",
        "store_number": "038943",
        "store_location": "https://www.google.com/maps/dir/?api=1&destination=47.504144821619406,-117.56533254684655"
      }
    ]
  },
  {
    "county_name": "Clarkston (1)",
    "county_url": "https://locations.tacobell.com/wa/clarkston",
    "stores": [
      {
        "store_page_url": "https://locations.tacobell.com/wa/clarkston/450-bridge-st.html",
        "store_number": "032590",
        "store_location": "https://www.google.com/maps/dir/?api=1&destination=46.42015107629563,-117.04343089875793"
      }
    ]
  },
  {
    "county_name": "Colville (1)",
    "county_url": "https://locations.tacobell.com/wa/colville",
    "stores": [
      {
        "store_page_url": "https://locations.tacobell.com/wa/colville/1520-n--highway-395.html",
        "store_number": "C748053",
        "store_location": "https://www.google.com/maps/dir/?api=1&destination=48.557572761445854,-117.92379543185234"
      }
    ]
  },
  {
    "county_name": "Covington (1)",
    "county_url": "https://locations.tacobell.com/wa/covington",
    "stores": [
      {
        "store_page_url": "https://locations.tacobell.com/wa/covington/17425-se-272nd-st-.html",
        "store_number": "E720429",
        "store_location": "https://www.google.com/maps/dir/?api=1&destination=47.357909766427625,-122.10939816668542"
      }
    ]
  },
  {
    "county_name": "Deer Park (1)",
    "county_url": "https://locations.tacobell.com/wa/deer-park",
    "stores": [
      {
        "store_page_url": "https://locations.tacobell.com/wa/deer-park/807-s-main-ave.html",
        "store_number": "038951",
        "store_location": "https://www.google.com/maps/dir/?api=1&destination=47.94646269012617,-117.47665164947239"
      }
    ]
  },
  {
    "county_name": "Des Moines (1)",
    "county_url": "https://locations.tacobell.com/wa/des-moines",
    "stores": [
      {
        "store_page_url": "https://locations.tacobell.com/wa/des-moines/27001-pacific-hwy-s.html",
        "store_number": "031320",
        "store_location": "https://www.google.com/maps/dir/?api=1&destination=47.359519254261876,-122.30901353419219"
      }
    ]
  },
  {
    "county_name": "East Wenatchee (1)",
    "county_url": "https://locations.tacobell.com/wa/east-wenatchee",
    "stores": [
      {
        "store_page_url": "https://locations.tacobell.com/wa/east-wenatchee/410-valley-mall-parkway.html",
        "store_number": "C150002",
        "store_location": "https://www.google.com/maps/dir/?api=1&destination=47.40975434526554,-120.29004827141762"
      }
    ]
  },
  {
    "county_name": "Edmonds (1)",
    "county_url": "https://locations.tacobell.com/wa/edmonds",
    "stores": [
      {
        "store_page_url": "https://locations.tacobell.com/wa/edmonds/10119-edmonds-way.html",
        "store_number": "022609",
        "store_location": "https://www.google.com/maps/dir/?api=1&destination=47.79225917732412,-122.36915878954278"
      }
    ]
  },
  {
    "county_name": "Ellensburg (1)",
    "county_url": "https://locations.tacobell.com/wa/ellensburg",
    "stores": [
      {
        "store_page_url": "https://locations.tacobell.com/wa/ellensburg/1406-s-canyon-rd.html",
        "store_number": "022515",
        "store_location": "https://www.google.com/maps/dir/?api=1&destination=46.97922203293111,-120.54320184281096"
      }
    ]
  },
  {
    "county_name": "Enumclaw (1)",
    "county_url": "https://locations.tacobell.com/wa/enumclaw",
    "stores": [
      {
        "store_page_url": "https://locations.tacobell.com/wa/enumclaw/727-roosevelt-avenue.html",
        "store_number": "035632",
        "store_location": "https://www.google.com/maps/dir/?api=1&destination=47.19979450257849,-121.98721417455425"
      }
    ]
  },
  {
    "county_name": "Ephrata (1)",
    "county_url": "https://locations.tacobell.com/wa/ephrata",
    "stores": [
      {
        "store_page_url": "https://locations.tacobell.com/wa/ephrata/1305-basin-st.html",
        "store_number": "038950",
        "store_location": "https://www.google.com/maps/dir/?api=1&destination=47.307581122312314,-119.56167429685593"
      }
    ]
  },
  {
    "county_name": "Everett (4)",
    "county_url": "https://locations.tacobell.com/wa/everett",
    "stores": [
      {
        "store_page_url": "https://locations.tacobell.com/wa/everett/7431-evergreen-way.html",
        "store_number": "031341",
        "store_location": "https://www.google.com/maps/dir/?api=1&destination=47.93033299483421,-122.22021813970059"
      },
      {
        "store_page_url": "https://locations.tacobell.com/wa/everett/515-sw-128th-street.html",
        "store_number": "031336",
        "store_location": "https://www.google.com/maps/dir/?api=1&destination=47.88228681872977,-122.24091142416"
      },
      {
        "store_page_url": "https://locations.tacobell.com/wa/everett/5006-132nd-street-se.html",
        "store_number": "031334",
        "store_location": "https://www.google.com/maps/dir/?api=1&destination=47.87732620047068,-122.16392416292845"
      },
      {
        "store_page_url": "https://locations.tacobell.com/wa/everett/2727-broadway-st.html",
        "store_number": "022602",
        "store_location": "https://www.google.com/maps/dir/?api=1&destination=47.9809238465088,-122.20114446112193"
      }
    ]
  },
  {
    "county_name": "Federal Way (3)",
    "county_url": "https://locations.tacobell.com/wa/federal-way",
    "stores": [
      {
        "store_page_url": "https://locations.tacobell.com/wa/federal-way/2031-s-w--campus-drive.html",
        "store_number": "031328",
        "store_location": "https://www.google.com/maps/dir/?api=1&destination=47.30041944150067,-122.36050925686868"
      },
      {
        "store_page_url": "https://locations.tacobell.com/wa/federal-way/1330-s-348th-st.html",
        "store_number": "031329",
        "store_location": "https://www.google.com/maps/dir/?api=1&destination=47.290070639580264,-122.31657077373711"
      },
      {
        "store_page_url": "https://locations.tacobell.com/wa/federal-way/31533-pacific-hwy-s.html",
        "store_number": "038732",
        "store_location": "https://www.google.com/maps/dir/?api=1&destination=47.319,-122.314"
      }
    ]
  },
  {
    "county_name": "Ferndale (1)",
    "county_url": "https://locations.tacobell.com/wa/ferndale",
    "stores": [
      {
        "store_page_url": "https://locations.tacobell.com/wa/ferndale/5720-barrett-rd.html",
        "store_number": "034930",
        "store_location": "https://www.google.com/maps/dir/?api=1&destination=48.84922576328191,-122.57324520849482"
      }
    ]
  },
  {
    "county_name": "Fife (1)",
    "county_url": "https://locations.tacobell.com/wa/fife",
    "stores": [
      {
        "store_page_url": "https://locations.tacobell.com/wa/fife/5152-pacific-highway-east.html",
        "store_number": "031327",
        "store_location": "https://www.google.com/maps/dir/?api=1&destination=47.24275914362729,-122.36008733510971"
      }
    ]
  },
  {
    "county_name": "Kelso (1)",
    "county_url": "https://locations.tacobell.com/wa/kelso",
    "stores": [
      {
        "store_page_url": "https://locations.tacobell.com/wa/kelso/1009-allen-st.html",
        "store_number": "004946",
        "store_location": "https://www.google.com/maps/dir/?api=1&destination=46.14413541270274,-122.90087966015562"
      }
    ]
  },
  {
    "county_name": "Kennewick (3)",
    "county_url": "https://locations.tacobell.com/wa/kennewick",
    "stores": [
      {
        "store_page_url": "https://locations.tacobell.com/wa/kennewick/901-north-columbia-center-boulevard.html",
        "store_number": "E720384",
        "store_location": "https://www.google.com/maps/dir/?api=1&destination=46.220478687691624,-119.22478348016739"
      },
      {
        "store_page_url": "https://locations.tacobell.com/wa/kennewick/3623-plaza-way.html",
        "store_number": "032196",
        "store_location": "https://www.google.com/maps/dir/?api=1&destination=46.17879162640969,-119.18799293096203"
      },
      {
        "store_page_url": "https://locations.tacobell.com/wa/kennewick/2718-w-kennewick-ave.html",
        "store_number": "022514",
        "store_location": "https://www.google.com/maps/dir/?api=1&destination=46.20978835528004,-119.15847236896991"
      }
    ]
  },
  {
    "county_name": "Kent (2)",
    "county_url": "https://locations.tacobell.com/wa/kent",
    "stores": [
      {
        "store_page_url": "https://locations.tacobell.com/wa/kent/322-washington-ave-south.html",
        "store_number": "031323",
        "store_location": "https://www.google.com/maps/dir/?api=1&destination=47.378975401337506,-122.24698354305474"
      },
      {
        "store_page_url": "https://locations.tacobell.com/wa/kent/23920-104th-avenue-s-e-.html",
        "store_number": "031346",
        "store_location": "https://www.google.com/maps/dir/?api=1&destination=47.387204356751106,-122.20177987221172"
      }
    ]
  },
  {
    "county_name": "Kirkland (1)",
    "county_url": "https://locations.tacobell.com/wa/kirkland",
    "stores": [
      {
        "store_page_url": "https://locations.tacobell.com/wa/kirkland/11624-124th-ne.html",
        "store_number": "035308",
        "store_location": "https://www.google.com/maps/dir/?api=1&destination=47.704744196233236,-122.17530570929739"
      }
    ]
  },
  {
    "county_name": "Lacey (4)",
    "county_url": "https://locations.tacobell.com/wa/lacey",
    "stores": [
      {
        "store_page_url": "https://locations.tacobell.com/wa/lacey/5650-martin-way.html",
        "store_number": "035312",
        "store_location": "https://www.google.com/maps/dir/?api=1&destination=47.04986811863236,-122.80902474070899"
      },
      {
        "store_page_url": "https://locations.tacobell.com/wa/lacey/5520-corporate-center-lane-se.html",
        "store_number": "035321",
        "store_location": "https://www.google.com/maps/dir/?api=1&destination=46.998186,-122.824235"
      },
      {
        "store_page_url": "https://locations.tacobell.com/wa/lacey/3815-pacific-avenue-s-e-.html",
        "store_number": "031337",
        "store_location": "https://www.google.com/maps/dir/?api=1&destination=47.03973509496678,-122.83757262509855"
      },
      {
        "store_page_url": "https://locations.tacobell.com/wa/lacey/8306-quinault-drive-ne.html",
        "store_number": "036792",
        "store_location": "https://www.google.com/maps/dir/?api=1&destination=47.062226295319995,-122.76396739065683"
      }
    ]
  },
  {
    "county_name": "Lake Stevens (1)",
    "county_url": "https://locations.tacobell.com/wa/lake-stevens",
    "stores": [
      {
        "store_page_url": "https://locations.tacobell.com/wa/lake-stevens/303-91st-ave-ne.html",
        "store_number": "022605",
        "store_location": "https://www.google.com/maps/dir/?api=1&destination=47.998161514148876,-122.10805786011883"
      }
    ]
  },
  {
    "county_name": "Lakewood (3)",
    "county_url": "https://locations.tacobell.com/wa/lakewood",
    "stores": [
      {
        "store_page_url": "https://locations.tacobell.com/wa/lakewood/9511-bridgeport-way-sw.html",
        "store_number": "031331",
        "store_location": "https://www.google.com/maps/dir/?api=1&destination=47.1710277410081,-122.51696437597275"
      },
      {
        "store_page_url": "https://locations.tacobell.com/wa/lakewood/8401-s--tacoma-way.html",
        "store_number": "031324",
        "store_location": "https://www.google.com/maps/dir/?api=1&destination=47.18080199222686,-122.48338832521767"
      },
      {
        "store_page_url": "https://locations.tacobell.com/wa/lakewood/15223-union-ave-sw.html",
        "store_number": "031317",
        "store_location": "https://www.google.com/maps/dir/?api=1&destination=47.120501289375504,-122.55532481937847"
      }
    ]
  },
  {
    "county_name": "Liberty Lake (1)",
    "county_url": "https://locations.tacobell.com/wa/liberty-lake",
    "stores": [
      {
        "store_page_url": "https://locations.tacobell.com/wa/liberty-lake/22312-e-apple-way.html",
        "store_number": "038944",
        "store_location": "https://www.google.com/maps/dir/?api=1&destination=47.67161747570849,-117.1046439707606"
      }
    ]
  },
  {
    "county_name": "Longview (2)",
    "county_url": "https://locations.tacobell.com/wa/longview",
    "stores": [
      {
        "store_page_url": "https://locations.tacobell.com/wa/longview/830-ocean-beach-hwy.html",
        "store_number": "020555",
        "store_location": "https://www.google.com/maps/dir/?api=1&destination=46.146705707562,-122.92752300204484"
      },
      {
        "store_page_url": "https://locations.tacobell.com/wa/longview/3740-ocean-beach-hwy.html",
        "store_number": "040473",
        "store_location": "https://www.google.com/maps/dir/?api=1&destination=46.1555938,-122.9823091"
      }
    ]
  },
  {
    "county_name": "Lynden (1)",
    "county_url": "https://locations.tacobell.com/wa/lynden",
    "stores": [
      {
        "store_page_url": "https://locations.tacobell.com/wa/lynden/8169-guide-meridian-rd-.html",
        "store_number": "040918",
        "store_location": "https://www.google.com/maps/dir/?api=1&destination=48.93754777271098,-122.48602126456785"
      }
    ]
  },
  {
    "county_name": "Lynnwood (2)",
    "county_url": "https://locations.tacobell.com/wa/lynnwood",
    "stores": [
      {
        "store_page_url": "https://locations.tacobell.com/wa/lynnwood/4919-196th-street-s-w.html",
        "store_number": "022607",
        "store_location": "https://www.google.com/maps/dir/?api=1&destination=47.821453816163455,-122.30010028646434"
      },
      {
        "store_page_url": "https://locations.tacobell.com/wa/lynnwood/14827-hwy-99.html",
        "store_number": "022603",
        "store_location": "https://www.google.com/maps/dir/?api=1&destination=47.863294804877654,-122.28221123345702"
      }
    ]
  },
  {
    "county_name": "Maple Valley (1)",
    "county_url": "https://locations.tacobell.com/wa/maple-valley",
    "stores": [
      {
        "store_page_url": "https://locations.tacobell.com/wa/maple-valley/23848-225th-st--s-e-.html",
        "store_number": "E720421",
        "store_location": "https://www.google.com/maps/dir/?api=1&destination=47.38777898519353,-122.04173775628865"
      }
    ]
  },
  {
    "county_name": "Marysville (3)",
    "county_url": "https://locations.tacobell.com/wa/marysville",
    "stores": [
      {
        "store_page_url": "https://locations.tacobell.com/wa/marysville/616-state-street.html",
        "store_number": "031335",
        "store_location": "https://www.google.com/maps/dir/?api=1&destination=48.05431113558973,-122.17652499675751"
      },
      {
        "store_page_url": "https://locations.tacobell.com/wa/marysville/3729-116th-st-ne.html",
        "store_number": "035318",
        "store_location": "https://www.google.com/maps/dir/?api=1&destination=48.10029352780463,-122.18114644289017"
      },
      {
        "store_page_url": "https://locations.tacobell.com/wa/marysville/17105-27th-avenue-ne.html",
        "store_number": "035317",
        "store_location": "https://www.google.com/maps/dir/?api=1&destination=48.151921779099055,-122.19325232712595"
      }
    ]
  },
  {
    "county_name": "Milton (1)",
    "county_url": "https://locations.tacobell.com/wa/milton",
    "stores": [
      {
        "store_page_url": "https://locations.tacobell.com/wa/milton/328-meridian-avenue-east.html",
        "store_number": "035322",
        "store_location": "https://www.google.com/maps/dir/?api=1&destination=47.2533694,-122.2942162"
      }
    ]
  },
  {
    "county_name": "Monroe (1)",
    "county_url": "https://locations.tacobell.com/wa/monroe",
    "stores": [
      {
        "store_page_url": "https://locations.tacobell.com/wa/monroe/19025-state-route-2.html",
        "store_number": "035313",
        "store_location": "https://www.google.com/maps/dir/?api=1&destination=47.86084201380594,-121.97560876607895"
      }
    ]
  },
  {
    "county_name": "Moses Lake (2)",
    "county_url": "https://locations.tacobell.com/wa/moses-lake",
    "stores": [
      {
        "store_page_url": "https://locations.tacobell.com/wa/moses-lake/934-n-stratford-rd.html",
        "store_number": "038939",
        "store_location": "https://www.google.com/maps/dir/?api=1&destination=47.14162820328876,-119.27866987422021"
      },
      {
        "store_page_url": "https://locations.tacobell.com/wa/moses-lake/2401-s-maiers-rd.html",
        "store_number": "038948",
        "store_location": "https://www.google.com/maps/dir/?api=1&destination=47.10327805245132,-119.24977641311163"
      }
    ]
  },
  {
    "county_name": "Mount Vernon (1)",
    "county_url": "https://locations.tacobell.com/wa/mount-vernon",
    "stores": [
      {
        "store_page_url": "https://locations.tacobell.com/wa/mount-vernon/217-east-college-way.html",
        "store_number": "031342",
        "store_location": "https://www.google.com/maps/dir/?api=1&destination=48.43619811528398,-122.33817234635347"
      }
    ]
  },
  {
    "county_name": "Mukilteo (1)",
    "county_url": "https://locations.tacobell.com/wa/mukilteo",
    "stores": [
      {
        "store_page_url": "https://locations.tacobell.com/wa/mukilteo/8401-mukilteo-speedway.html",
        "store_number": "022604",
        "store_location": "https://www.google.com/maps/dir/?api=1&destination=47.921772161868205,-122.29962104089455"
      }
    ]
  },
  {
    "county_name": "Napavine (1)",
    "county_url": "https://locations.tacobell.com/wa/napavine",
    "stores": [
      {
        "store_page_url": "https://locations.tacobell.com/wa/napavine/1245-rush-rd-.html",
        "store_number": "035319",
        "store_location": "https://www.google.com/maps/dir/?api=1&destination=46.6043,-122.909"
      }
    ]
  },
  {
    "county_name": "Oak Harbor (1)",
    "county_url": "https://locations.tacobell.com/wa/oak-harbor",
    "stores": [
      {
        "store_page_url": "https://locations.tacobell.com/wa/oak-harbor/32780-state-highway-20.html",
        "store_number": "031343",
        "store_location": "https://www.google.com/maps/dir/?api=1&destination=48.30445809943917,-122.64523525537697"
      }
    ]
  },
  {
    "county_name": "Olympia (2)",
    "county_url": "https://locations.tacobell.com/wa/olympia",
    "stores": [
      {
        "store_page_url": "https://locations.tacobell.com/wa/olympia/1101-cooper-point-rd-sw.html",
        "store_number": "031338",
        "store_location": "https://www.google.com/maps/dir/?api=1&destination=47.037954209941596,-122.93981842702124"
      },
      {
        "store_page_url": "https://locations.tacobell.com/wa/olympia/2725-93rd-ave--sw.html",
        "store_number": "037678",
        "store_location": "https://www.google.com/maps/dir/?api=1&destination=46.95179309559345,-122.94052644299336"
      }
    ]
  },
  {
    "county_name": "Omak (1)",
    "county_url": "https://locations.tacobell.com/wa/omak",
    "stores": [
      {
        "store_page_url": "https://locations.tacobell.com/wa/omak/620-omache-drive.html",
        "store_number": "C150009",
        "store_location": "https://www.google.com/maps/dir/?api=1&destination=48.41807749164281,-119.50778051281304"
      }
    ]
  },
  {
    "county_name": "Othello (1)",
    "county_url": "https://locations.tacobell.com/wa/othello",
    "stores": [
      {
        "store_page_url": "https://locations.tacobell.com/wa/othello/1820-east-main-st-.html",
        "store_number": "038949",
        "store_location": "https://www.google.com/maps/dir/?api=1&destination=46.825916484524676,-119.14831906557083"
      }
    ]
  },
  {
    "county_name": "Pasco (2)",
    "county_url": "https://locations.tacobell.com/wa/pasco",
    "stores": [
      {
        "store_page_url": "https://locations.tacobell.com/wa/pasco/5105-north-road-68.html",
        "store_number": "042765",
        "store_location": "https://www.google.com/maps/dir/?api=1&destination=46.27343102621953,-119.1843330860138"
      },
      {
        "store_page_url": "https://locations.tacobell.com/wa/pasco/2404-west-court-street.html",
        "store_number": "022517",
        "store_location": "https://www.google.com/maps/dir/?api=1&destination=46.24120106145248,-119.12287294864655"
      }
    ]
  },
  {
    "county_name": "Port Angeles (1)",
    "county_url": "https://locations.tacobell.com/wa/port-angeles",
    "stores": [
      {
        "store_page_url": "https://locations.tacobell.com/wa/port-angeles/2001-east-first-street.html",
        "store_number": "E143010",
        "store_location": "https://www.google.com/maps/dir/?api=1&destination=48.106722123695356,-123.3996762782499"
      }
    ]
  },
  {
    "county_name": "Port Orchard (1)",
    "county_url": "https://locations.tacobell.com/wa/port-orchard",
    "stores": [
      {
        "store_page_url": "https://locations.tacobell.com/wa/port-orchard/3458-se-mile-hill-dr.html",
        "store_number": "037298",
        "store_location": "https://www.google.com/maps/dir/?api=1&destination=47.5335657,-122.60758"
      }
    ]
  },
  {
    "county_name": "Poulsbo (1)",
    "county_url": "https://locations.tacobell.com/wa/poulsbo",
    "stores": [
      {
        "store_page_url": "https://locations.tacobell.com/wa/poulsbo/21289-olhava-way.html",
        "store_number": "042279",
        "store_location": "https://www.google.com/maps/dir/?api=1&destination=47.7561815,-122.6595238"
      }
    ]
  },
  {
    "county_name": "Prosser (1)",
    "county_url": "https://locations.tacobell.com/wa/prosser",
    "stores": [
      {
        "store_page_url": "https://locations.tacobell.com/wa/prosser/109-merlot-drive.html",
        "store_number": "E720389",
        "store_location": "https://www.google.com/maps/dir/?api=1&destination=46.220345941224586,-119.7877818136476"
      }
    ]
  },
  {
    "county_name": "Pullman (1)",
    "county_url": "https://locations.tacobell.com/wa/pullman",
    "stores": [
      {
        "store_page_url": "https://locations.tacobell.com/wa/pullman/425-ne-stadium-way.html",
        "store_number": "029831",
        "store_location": "https://www.google.com/maps/dir/?api=1&destination=46.738732,-117.171069"
      }
    ]
  },
  {
    "county_name": "Puyallup (5)",
    "county_url": "https://locations.tacobell.com/wa/puyallup",
    "stores": [
      {
        "store_page_url": "https://locations.tacobell.com/wa/puyallup/702-s-meridian.html",
        "store_number": "031339",
        "store_location": "https://www.google.com/maps/dir/?api=1&destination=47.185739572784506,-122.29398019147078"
      },
      {
        "store_page_url": "https://locations.tacobell.com/wa/puyallup/17514-meridian-east.html",
        "store_number": "E720425",
        "store_location": "https://www.google.com/maps/dir/?api=1&destination=47.09812786324255,-122.2951137201414"
      },
      {
        "store_page_url": "https://locations.tacobell.com/wa/puyallup/12223-meridian-st.html",
        "store_number": "031314",
        "store_location": "https://www.google.com/maps/dir/?api=1&destination=47.14509633338393,-122.29247689247131"
      },
      {
        "store_page_url": "https://locations.tacobell.com/wa/puyallup/11304-canyon-road.html",
        "store_number": "031330",
        "store_location": "https://www.google.com/maps/dir/?api=1&destination=47.15267936018919,-122.3575821518898"
      },
      {
        "store_page_url": "https://locations.tacobell.com/wa/puyallup/724-shaw-rd--east.html",
        "store_number": "036426",
        "store_location": "https://www.google.com/maps/dir/?api=1&destination=47.18437939720152,-122.25693117255726"
      }
    ]
  },
  {
    "county_name": "Redmond (1)",
    "county_url": "https://locations.tacobell.com/wa/redmond",
    "stores": [
      {
        "store_page_url": "https://locations.tacobell.com/wa/redmond/1960-148th-avenue-n-e-.html",
        "store_number": "031340",
        "store_location": "https://www.google.com/maps/dir/?api=1&destination=47.627458123612854,-122.14273050427437"
      }
    ]
  },
  {
    "county_name": "Renton (2)",
    "county_url": "https://locations.tacobell.com/wa/renton",
    "stores": [
      {
        "store_page_url": "https://locations.tacobell.com/wa/renton/320-rainier-avenue-south.html",
        "store_number": "031344",
        "store_location": "https://www.google.com/maps/dir/?api=1&destination=47.479041039554396,-122.21612432602342"
      },
      {
        "store_page_url": "https://locations.tacobell.com/wa/renton/17809-108th-ave-s-e.html",
        "store_number": "031313",
        "store_location": "https://www.google.com/maps/dir/?api=1&destination=47.44270751771033,-122.197379395393"
      }
    ]
  },
  {
    "county_name": "Richland (2)",
    "county_url": "https://locations.tacobell.com/wa/richland",
    "stores": [
      {
        "store_page_url": "https://locations.tacobell.com/wa/richland/2485-queensgate-dr-.html",
        "store_number": "024328",
        "store_location": "https://www.google.com/maps/dir/?api=1&destination=46.25693099804831,-119.30635575951777"
      },
      {
        "store_page_url": "https://locations.tacobell.com/wa/richland/1825-george-washington-way.html",
        "store_number": "042758",
        "store_location": "https://www.google.com/maps/dir/?api=1&destination=46.299960761411626,-119.27468866109848"
      }
    ]
  },
  {
    "county_name": "Ridgefield (1)",
    "county_url": "https://locations.tacobell.com/wa/ridgefield",
    "stores": [
      {
        "store_page_url": "https://locations.tacobell.com/wa/ridgefield/50-s--48th-place.html",
        "store_number": "036344",
        "store_location": "https://www.google.com/maps/dir/?api=1&destination=45.81521068263736,-122.7031338757779"
      }
    ]
  },
  {
    "county_name": "Rochester (1)",
    "county_url": "https://locations.tacobell.com/wa/rochester",
    "stores": [
      {
        "store_page_url": "https://locations.tacobell.com/wa/rochester/19704-old-hwy-99-sw.html",
        "store_number": "037010",
        "store_location": "https://www.google.com/maps/dir/?api=1&destination=46.80200978235368,-123.01137629161197"
      }
    ]
  },
  {
    "county_name": "Seatac (1)",
    "county_url": "https://locations.tacobell.com/wa/seatac",
    "stores": [
      {
        "store_page_url": "https://locations.tacobell.com/wa/seatac/18812-international-blvd-.html",
        "store_number": "035311",
        "store_location": "https://www.google.com/maps/dir/?api=1&destination=47.4342073549156,-122.2950821323684"
      }
    ]
  },
  {
    "county_name": "Seattle (7)",
    "county_url": "https://locations.tacobell.com/wa/seattle",
    "stores": [
      {
        "store_page_url": "https://locations.tacobell.com/wa/seattle/2201-4th-avenue-south.html",
        "store_number": "E720450",
        "store_location": "https://www.google.com/maps/dir/?api=1&destination=47.583848151037735,-122.32951377333848"
      },
      {
        "store_page_url": "https://locations.tacobell.com/wa/seattle/210-w--mercer-st-.html",
        "store_number": "D181003",
        "store_location": "https://www.google.com/maps/dir/?api=1&destination=47.62435834895249,-122.3596047263002"
      },
      {
        "store_page_url": "https://locations.tacobell.com/wa/seattle/14506-bothell-way-ne.html",
        "store_number": "022599",
        "store_location": "https://www.google.com/maps/dir/?api=1&destination=47.734071758808284,-122.2921140566632"
      },
      {
        "store_page_url": "https://locations.tacobell.com/wa/seattle/1110-north-90th-street.html",
        "store_number": "035314",
        "store_location": "https://www.google.com/maps/dir/?api=1&destination=47.69445801371516,-122.3440209031105"
      },
      {
        "store_page_url": "https://locations.tacobell.com/wa/seattle/10711-16th-ave-sw.html",
        "store_number": "031311",
        "store_location": "https://www.google.com/maps/dir/?api=1&destination=47.50672080526724,-122.35538444980772"
      },
      {
        "store_page_url": "https://locations.tacobell.com/wa/seattle/9401-rainier-ave--s.html",
        "store_number": "E720399",
        "store_location": "https://www.google.com/maps/dir/?api=1&destination=47.51963527100156,-122.26467043161392"
      },
      {
        "store_page_url": "https://locations.tacobell.com/wa/seattle/5918-15th-avenue-nw.html",
        "store_number": "035315",
        "store_location": "https://www.google.com/maps/dir/?api=1&destination=47.6720975462472,-122.37581714987755"
      }
    ]
  },
  {
    "county_name": "Selah (1)",
    "county_url": "https://locations.tacobell.com/wa/selah",
    "stores": [
      {
        "store_page_url": "https://locations.tacobell.com/wa/selah/721-n-park-ctr.html",
        "store_number": "042766",
        "store_location": "https://www.google.com/maps/dir/?api=1&destination=46.664037691041344,-120.52170394459571"
      }
    ]
  },
  {
    "county_name": "Sequim (1)",
    "county_url": "https://locations.tacobell.com/wa/sequim",
    "stores": [
      {
        "store_page_url": "https://locations.tacobell.com/wa/sequim/11-lee-chatfield-way.html",
        "store_number": "042281",
        "store_location": "https://www.google.com/maps/dir/?api=1&destination=48.077085551853656,-123.08886878197882"
      }
    ]
  },
  {
    "county_name": "Shelton (1)",
    "county_url": "https://locations.tacobell.com/wa/shelton",
    "stores": [
      {
        "store_page_url": "https://locations.tacobell.com/wa/shelton/301-wallace-kneeland-blvd.html",
        "store_number": "031326",
        "store_location": "https://www.google.com/maps/dir/?api=1&destination=47.23133846398098,-123.12308972883608"
      }
    ]
  },
  {
    "county_name": "Silverdale (1)",
    "county_url": "https://locations.tacobell.com/wa/silverdale",
    "stores": [
      {
        "store_page_url": "https://locations.tacobell.com/wa/silverdale/3051-nw-bucklin-hill-rd.html",
        "store_number": "037297",
        "store_location": "https://www.google.com/maps/dir/?api=1&destination=47.65028744452106,-122.6898707871288"
      }
    ]
  },
  {
    "county_name": "Snohomish (1)",
    "county_url": "https://locations.tacobell.com/wa/snohomish",
    "stores": [
      {
        "store_page_url": "https://locations.tacobell.com/wa/snohomish/1100-avenue-d.html",
        "store_number": "022608",
        "store_location": "https://www.google.com/maps/dir/?api=1&destination=47.924857437965144,-122.09822550418721"
      }
    ]
  },
  {
    "county_name": "Spanaway (1)",
    "county_url": "https://locations.tacobell.com/wa/spanaway",
    "stores": [
      {
        "store_page_url": "https://locations.tacobell.com/wa/spanaway/20527-mountain-highway-e.html",
        "store_number": "037113",
        "store_location": "https://www.google.com/maps/dir/?api=1&destination=47.0704,-122.417"
      }
    ]
  },
  {
    "county_name": "Spokane (9)",
    "county_url": "https://locations.tacobell.com/wa/spokane",
    "stores": [
      {
        "store_page_url": "https://locations.tacobell.com/wa/spokane/9664-n-newport-hwy.html",
        "store_number": "038937",
        "store_location": "https://www.google.com/maps/dir/?api=1&destination=47.747615,-117.403036"
      },
      {
        "store_page_url": "https://locations.tacobell.com/wa/spokane/825-w-3rd-ave.html",
        "store_number": "038936",
        "store_location": "https://www.google.com/maps/dir/?api=1&destination=47.65317817774261,-117.42466451685718"
      },
      {
        "store_page_url": "https://locations.tacobell.com/wa/spokane/6614-n-division-st.html",
        "store_number": "038938",
        "store_location": "https://www.google.com/maps/dir/?api=1&destination=47.71785728984489,-117.41070357849821"
      },
      {
        "store_page_url": "https://locations.tacobell.com/wa/spokane/4101-no-market-st.html",
        "store_number": "038946",
        "store_location": "https://www.google.com/maps/dir/?api=1&destination=47.695778311196115,-117.36563220625612"
      },
      {
        "store_page_url": "https://locations.tacobell.com/wa/spokane/3010-east-29th-avenue.html",
        "store_number": "038945",
        "store_location": "https://www.google.com/maps/dir/?api=1&destination=47.6280058449103,-117.36691117286682"
      },
      {
        "store_page_url": "https://locations.tacobell.com/wa/spokane/1202-n-monroe-st.html",
        "store_number": "038940",
        "store_location": "https://www.google.com/maps/dir/?api=1&destination=47.66834607573968,-117.42613328704803"
      },
      {
        "store_page_url": "https://locations.tacobell.com/wa/spokane/10620-east-sprague-avenue.html",
        "store_number": "038941",
        "store_location": "https://www.google.com/maps/dir/?api=1&destination=47.656825325244256,-117.26191602497205"
      },
      {
        "store_page_url": "https://locations.tacobell.com/wa/spokane/10510-w-sr-2.html",
        "store_number": "038947",
        "store_location": "https://www.google.com/maps/dir/?api=1&destination=47.643522651538476,-117.55784348400084"
      },
      {
        "store_page_url": "https://locations.tacobell.com/wa/spokane/6404-n--ash-st--.html",
        "store_number": "038952",
        "store_location": "https://www.google.com/maps/dir/?api=1&destination=47.716538237958495,-117.4358294339931"
      }
    ]
  },
  {
    "county_name": "Spokane Valley (1)",
    "county_url": "https://locations.tacobell.com/wa/spokane-valley",
    "stores": [
      {
        "store_page_url": "https://locations.tacobell.com/wa/spokane-valley/133-n-sullivan-rd.html",
        "store_number": "038942",
        "store_location": "https://www.google.com/maps/dir/?api=1&destination=47.65864559164108,-117.19702541828156"
      }
    ]
  },
  {
    "county_name": "Sunnyside (1)",
    "county_url": "https://locations.tacobell.com/wa/sunnyside",
    "stores": [
      {
        "store_page_url": "https://locations.tacobell.com/wa/sunnyside/2550-yakima-valley-hwy.html",
        "store_number": "042759",
        "store_location": "https://www.google.com/maps/dir/?api=1&destination=46.31984145982773,-119.98727753794651"
      }
    ]
  },
  {
    "county_name": "Tacoma (7)",
    "county_url": "https://locations.tacobell.com/wa/tacoma",
    "stores": [
      {
        "store_page_url": "https://locations.tacobell.com/wa/tacoma/2945-s-38th-st.html",
        "store_number": "031312",
        "store_location": "https://www.google.com/maps/dir/?api=1&destination=47.222808144691776,-122.47554396094529"
      },
      {
        "store_page_url": "https://locations.tacobell.com/wa/tacoma/2902-6th-avenue.html",
        "store_number": "031316",
        "store_location": "https://www.google.com/maps/dir/?api=1&destination=47.25504338858422,-122.4739115094394"
      },
      {
        "store_page_url": "https://locations.tacobell.com/wa/tacoma/2615-north-pearl-street.html",
        "store_number": "031318",
        "store_location": "https://www.google.com/maps/dir/?api=1&destination=47.27193904246022,-122.51521517338006"
      },
      {
        "store_page_url": "https://locations.tacobell.com/wa/tacoma/15611-pacific-ave.html",
        "store_number": "031315",
        "store_location": "https://www.google.com/maps/dir/?api=1&destination=47.11549485100983,-122.43434080484803"
      },
      {
        "store_page_url": "https://locations.tacobell.com/wa/tacoma/1404-e--72nd-street.html",
        "store_number": "031322",
        "store_location": "https://www.google.com/maps/dir/?api=1&destination=47.19146228228417,-122.41005152463913"
      },
      {
        "store_page_url": "https://locations.tacobell.com/wa/tacoma/10611-pacific-ave.html",
        "store_number": "031321",
        "store_location": "https://www.google.com/maps/dir/?api=1&destination=47.160731525872336,-122.43381087954022"
      },
      {
        "store_page_url": "https://locations.tacobell.com/wa/tacoma/5308-176th-st--east.html",
        "store_number": "035320",
        "store_location": "https://www.google.com/maps/dir/?api=1&destination=47.09585058787434,-122.35877305269241"
      }
    ]
  },
  {
    "county_name": "Toppenish (1)",
    "county_url": "https://locations.tacobell.com/wa/toppenish",
    "stores": [
      {
        "store_page_url": "https://locations.tacobell.com/wa/toppenish/415-south-elm-street.html",
        "store_number": "E720194",
        "store_location": "https://www.google.com/maps/dir/?api=1&destination=46.374377566388496,-120.3206630051136"
      }
    ]
  },
  {
    "county_name": "Tukwila (2)",
    "county_url": "https://locations.tacobell.com/wa/tukwila",
    "stores": [
      {
        "store_page_url": "https://locations.tacobell.com/wa/tukwila/16350-w-valley-hwy.html",
        "store_number": "031325",
        "store_location": "https://www.google.com/maps/dir/?api=1&destination=47.457099726046366,-122.24341319685163"
      },
      {
        "store_page_url": "https://locations.tacobell.com/wa/tukwila/15036-tukwila-international-blvd-.html",
        "store_number": "E720401",
        "store_location": "https://www.google.com/maps/dir/?api=1&destination=47.467765464403136,-122.28708404924487"
      }
    ]
  },
  {
    "county_name": "Tumwater (1)",
    "county_url": "https://locations.tacobell.com/wa/tumwater",
    "stores": [
      {
        "store_page_url": "https://locations.tacobell.com/wa/tumwater/182-trosper-rd-sw.html",
        "store_number": "035316",
        "store_location": "https://www.google.com/maps/dir/?api=1&destination=47.000268435455105,-122.91004322470599"
      }
    ]
  },
  {
    "county_name": "University Place (1)",
    "county_url": "https://locations.tacobell.com/wa/university-place",
    "stores": [
      {
        "store_page_url": "https://locations.tacobell.com/wa/university-place/6729-s--19th-street.html",
        "store_number": "031332",
        "store_location": "https://www.google.com/maps/dir/?api=1&destination=47.24303497021935,-122.52856350970433"
      }
    ]
  },
  {
    "county_name": "Vancouver (10)",
    "county_url": "https://locations.tacobell.com/wa/vancouver",
    "stores": [
      {
        "store_page_url": "https://locations.tacobell.com/wa/vancouver/8300-ne-vancouver-plaza-dr.html",
        "store_number": "004715",
        "store_location": "https://www.google.com/maps/dir/?api=1&destination=45.653467419865564,-122.5880734591261"
      },
      {
        "store_page_url": "https://locations.tacobell.com/wa/vancouver/7206-ne-highway-99.html",
        "store_number": "030834",
        "store_location": "https://www.google.com/maps/dir/?api=1&destination=45.67411408991987,-122.66385845794983"
      },
      {
        "store_page_url": "https://locations.tacobell.com/wa/vancouver/2600-north-general-anderson.html",
        "store_number": "018767",
        "store_location": "https://www.google.com/maps/dir/?api=1&destination=45.64041508612285,-122.62093578280655"
      },
      {
        "store_page_url": "https://locations.tacobell.com/wa/vancouver/15640-ne-fourth-plain-rd.html",
        "store_number": "026664",
        "store_location": "https://www.google.com/maps/dir/?api=1&destination=45.67258471564297,-122.512868642807"
      },
      {
        "store_page_url": "https://locations.tacobell.com/wa/vancouver/13204-n-e--hwy-99.html",
        "store_number": "015292",
        "store_location": "https://www.google.com/maps/dir/?api=1&destination=45.71658834602547,-122.65263532180242"
      },
      {
        "store_page_url": "https://locations.tacobell.com/wa/vancouver/1195-se-163rd-place.html",
        "store_number": "020147",
        "store_location": "https://www.google.com/maps/dir/?api=1&destination=45.61233194347561,-122.50470265746117"
      },
      {
        "store_page_url": "https://locations.tacobell.com/wa/vancouver/11717-ne-65th-street.html",
        "store_number": "019550",
        "store_location": "https://www.google.com/maps/dir/?api=1&destination=45.6695787079105,-122.55219496792051"
      },
      {
        "store_page_url": "https://locations.tacobell.com/wa/vancouver/11620-se-mill-plain-blvd.html",
        "store_number": "002252",
        "store_location": "https://www.google.com/maps/dir/?api=1&destination=45.621122790265375,-122.55227518117415"
      },
      {
        "store_page_url": "https://locations.tacobell.com/wa/vancouver/8605-ne-andreson.html",
        "store_number": "034708",
        "store_location": "https://www.google.com/maps/dir/?api=1&destination=45.68464910517399,-122.60184063463842"
      },
      {
        "store_page_url": "https://locations.tacobell.com/wa/vancouver/11606-ne-119th-street.html",
        "store_number": "037387",
        "store_location": "https://www.google.com/maps/dir/?api=1&destination=45.708885768435216,-122.55328347847339"
      }
    ]
  },
  {
    "county_name": "Walla Walla (1)",
    "county_url": "https://locations.tacobell.com/wa/walla-walla",
    "stores": [
      {
        "store_page_url": "https://locations.tacobell.com/wa/walla-walla/622-w-alder.html",
        "store_number": "037180",
        "store_location": "https://www.google.com/maps/dir/?api=1&destination=46.06263676184808,-118.34749733066238"
      }
    ]
  },
  {
    "county_name": "Wenatchee (1)",
    "county_url": "https://locations.tacobell.com/wa/wenatchee",
    "stores": [
      {
        "store_page_url": "https://locations.tacobell.com/wa/wenatchee/1300-north-miller-st.html",
        "store_number": "022518",
        "store_location": "https://www.google.com/maps/dir/?api=1&destination=47.43990533943494,-120.32515279950076"
      }
    ]
  },
  {
    "county_name": "Woodinville (1)",
    "county_url": "https://locations.tacobell.com/wa/woodinville",
    "stores": [
      {
        "store_page_url": "https://locations.tacobell.com/wa/woodinville/13405-ne-175th-st.html",
        "store_number": "026087",
        "store_location": "https://www.google.com/maps/dir/?api=1&destination=47.7541179990321,-122.16032824718025"
      }
    ]
  },
  {
    "county_name": "Woodland (1)",
    "county_url": "https://locations.tacobell.com/wa/woodland",
    "stores": [
      {
        "store_page_url": "https://locations.tacobell.com/wa/woodland/1478-dike-access-rd-.html",
        "store_number": "032952",
        "store_location": "https://www.google.com/maps/dir/?api=1&destination=45.9269514767942,-122.75907126953825"
      }
    ]
  },
  {
    "county_name": "Yakima (5)",
    "county_url": "https://locations.tacobell.com/wa/yakima",
    "stores": [
      {
        "store_page_url": "https://locations.tacobell.com/wa/yakima/716-e-yakima-ave.html",
        "store_number": "042761",
        "store_location": "https://www.google.com/maps/dir/?api=1&destination=46.60432048122081,-120.49587348106797"
      },
      {
        "store_page_url": "https://locations.tacobell.com/wa/yakima/4002-fruitvale-blvd.html",
        "store_number": "042760",
        "store_location": "https://www.google.com/maps/dir/?api=1&destination=46.62087183955774,-120.56155469927641"
      },
      {
        "store_page_url": "https://locations.tacobell.com/wa/yakima/230-s-72nd-ave.html",
        "store_number": "042762",
        "store_location": "https://www.google.com/maps/dir/?api=1&destination=46.594721526187776,-120.60483925047265"
      },
      {
        "store_page_url": "https://locations.tacobell.com/wa/yakima/2124-s-1st-street.html",
        "store_number": "042764",
        "store_location": "https://www.google.com/maps/dir/?api=1&destination=46.57065793999981,-120.4881601900356"
      },
      {
        "store_page_url": "https://locations.tacobell.com/wa/yakima/1602-w-nob-hill-blvd.html",
        "store_number": "042763",
        "store_location": "https://www.google.com/maps/dir/?api=1&destination=46.585020096747826,-120.53072621634101"
      }
    ]
  },
  {
    "county_name": "Yelm (1)",
    "county_url": "https://locations.tacobell.com/wa/yelm",
    "stores": [
      {
        "store_page_url": "https://locations.tacobell.com/wa/yelm/1310-e--yelm-avenue.html",
        "store_number": "C748044",
        "store_location": "https://www.google.com/maps/dir/?api=1&destination=46.933897426657616,-122.5910741277162"
      }
    ]
  }
]